freestuffs/__init__.py
freestuffs/city_list.py
freestuffs/stuff.py
freestuffs/stuff_charter.py
freestuffs/stuff_scraper.py
freestuffs-0.1.dist-info/DESCRIPTION.rst
freestuffs-0.1.dist-info/METADATA
freestuffs-0.1.dist-info/RECORD
freestuffs-0.1.dist-info/WHEEL
freestuffs-0.1.dist-info/metadata.json
freestuffs-0.1.dist-info/top_level.txt
