Metadata-Version: 2.0
Name: freestuffs
Version: 0.1
Summary: Find free stuff near you!
Home-page: https://github.com/polypmer/freestuffs
Author: Fenimore Love
Author-email: UNKNOWN
License: MIT
Platform: UNKNOWN
